rmnd_lca/__init__.py
rmnd_lca/activity_maps.py
rmnd_lca/cars.py
rmnd_lca/cement.py
rmnd_lca/clean_datasets.py
rmnd_lca/data_collection.py
rmnd_lca/ecoinvent_modification.py
rmnd_lca/electricity.py
rmnd_lca/export.py
rmnd_lca/geomap.py
rmnd_lca/inventory_imports.py
rmnd_lca/steel.py
rmnd_lca/utils.py
rmnd_lca/data/GAINStoREMINDtechmap.csv
rmnd_lca/data/dict_biosphere.txt
rmnd_lca/data/ecoinvent_to_gains_emission_mappping.csv
rmnd_lca/data/fix_names.csv
rmnd_lca/data/flows_biosphere.csv
rmnd_lca/data/fuel_co2_emission_factor.txt
rmnd_lca/data/fuels_lower_heating_value.txt
rmnd_lca/data/regionmappingH12.csv
rmnd_lca/data/additional_inventories/lci-Carma-CCS.xlsx
rmnd_lca/data/additional_inventories/lci-biofuels.xlsx
rmnd_lca/data/additional_inventories/lci-biogas.xlsx
rmnd_lca/data/additional_inventories/lci-geothermal.xlsx
rmnd_lca/data/additional_inventories/lci-hydrogen-coal-gasification.xlsx
rmnd_lca/data/additional_inventories/lci-hydrogen-electrolysis.xlsx
rmnd_lca/data/additional_inventories/lci-hydrogen-smr-atr-biogas.xlsx
rmnd_lca/data/additional_inventories/lci-hydrogen-smr-atr-natgas.xlsx
rmnd_lca/data/additional_inventories/lci-hydrogen-smr-biogas.xlsx
rmnd_lca/data/additional_inventories/lci-hydrogen-wood-gasification.xlsx
rmnd_lca/data/additional_inventories/lci-hydrogen.xlsx
rmnd_lca/data/additional_inventories/lci-lpg-from-methanol.xlsx
rmnd_lca/data/additional_inventories/lci-synfuel-from-coal.xlsx
rmnd_lca/data/additional_inventories/lci-synfuel.xlsx
rmnd_lca/data/additional_inventories/lci-synfuels-from-FT.xlsx
rmnd_lca/data/additional_inventories/lci-synfuels-from-methanol.xlsx
rmnd_lca/data/additional_inventories/lci-syngas-from-coal.xlsx
rmnd_lca/data/additional_inventories/lci-syngas.xlsx
rmnd_lca/data/cement/additional_data_GNR.csv
rmnd_lca/data/cement/clinker_ratio_ecoinvent_35.csv
rmnd_lca/data/cement/clinker_ratio_ecoinvent_36.csv
rmnd_lca/data/cement/clinker_ratios.csv
rmnd_lca/data/electricity/electricity_production_volumes_per_country.csv
rmnd_lca-0.1.6.dist-info/LICENSE
rmnd_lca-0.1.6.dist-info/METADATA
rmnd_lca-0.1.6.dist-info/WHEEL
rmnd_lca-0.1.6.dist-info/top_level.txt
rmnd_lca-0.1.6.dist-info/RECORD
