Metadata-Version: 2.1
Name: rmnd-lca
Version: 0.1.6
Summary: Coupling REMIND output to ecoinvent LCA database ecoinvent for prospective LCA
Home-page: https://github.com/romainsacchi/rmnd-lca
Author: Alois Dirnaichner <dirnaichner@pik-potsdam.de>, Chris Mutel <chris.mutel@psi.ch>, Tom Terlouw <tom.terlouw@psi.ch>, Romain Sacchi <romain.sacchi@psi.ch>
Author-email: UNKNOWN
License: BSD 3-Clause License
Requires-Dist: numpy
Requires-Dist: pytest-cov
Requires-Dist: coveralls
Requires-Dist: wurst (>=0.2)
Requires-Dist: bw2io
Requires-Dist: pandas
Requires-Dist: bw2data
Requires-Dist: brightway2
Requires-Dist: xarray (>0.15.0)
Requires-Dist: carculator (>=1.2.8)
Requires-Dist: prettytable
Requires-Dist: pycountry
